affective_rag/__init__.py
affective_rag/core/__init__.py
affective_rag/core/als.py
affective_rag/core/context_path_traversal.py
affective_rag/core/memory_store.py
affective_rag/examples/__init__.py
affective_rag/examples/logging_example.py
affective_rag/examples/no_spread_demo.py
affective_rag/examples/spreading_demo.py
affective_rag/examples/topk_demo.py
affective_rag/examples/unified_sampling_demo.py
affective_rag-0.1.0.dist-info/METADATA
affective_rag-0.1.0.dist-info/WHEEL
affective_rag-0.1.0.dist-info/licenses/LICENSE
affective_rag-0.1.0.dist-info/licenses/PATENTS
affective_rag-0.1.0.dist-info/RECORD
