Metadata-Version: 2.4
Name: affective-rag
Version: 0.1.0
Summary: A library for integrating episodic memory within AI applications.
Project-URL: Homepage, https://github.com/jeje1197/AffectiveRAG
Project-URL: Repository, https://github.com/jeje1197/AffectiveRAG
Project-URL: Issues, https://github.com/jeje1197/AffectiveRAG/issues
Author: Joseph Evans
License-Expression: Apache-2.0
License-File: LICENSE
License-File: PATENTS
Keywords: AI,Affective Computing,Affective Link Scoring,Context Path Traversal,Episodic Memory,Graph-RAG,RAG
Classifier: License :: OSI Approved :: Apache Software License
Classifier: Operating System :: OS Independent
Classifier: Programming Language :: Python :: 3
Requires-Python: >=3.11
Requires-Dist: networkx
Requires-Dist: numpy
Requires-Dist: pydantic
